CHANGELOG.md
CODE_OF_CONDUCT.md
LICENSE
MANIFEST.in
README.md
requirements.txt
setup.cfg
setup.py
examples/classifiers/Bacteriophage-structural-protein-classifier.ipynb
examples/embeddings/Bacteriophage-nucleotides-embedding.ipynb
examples/embeddings/Bacteriophage-proteins-embedding.ipynb
phages2050/__init__.py
phages2050.egg-info/PKG-INFO
phages2050.egg-info/SOURCES.txt
phages2050.egg-info/dependency_links.txt
phages2050.egg-info/requires.txt
phages2050.egg-info/top_level.txt
phages2050/classifiers/__init__.py
phages2050/classifiers/proteins/__init__.py
phages2050/classifiers/proteins/structural_protein.py
phages2050/crawlers/__init__.py
phages2050/crawlers/millardlab/__init__.py
phages2050/crawlers/millardlab/crawler.py
phages2050/crawlers/ncbi/__init__.py
phages2050/embeddings/__init__.py
phages2050/embeddings/nucleotides/__init__.py
phages2050/embeddings/nucleotides/word2vec.py
phages2050/embeddings/proteins/__init__.py
phages2050/embeddings/proteins/bert.py
phages2050/embeddings/proteins/esm.py
phages2050/features/__init__.py
phages2050/features/extractors/__init__.py
phages2050/features/extractors/proteins.py
phages2050/features/io/__init__.py
phages2050/features/io/fasta.py
phages2050/features/transformers/__init__.py
phages2050/features/transformers/kmers.py