Metadata-Version: 2.1
Name: phages2050
Version: 0.0.7
Summary: PHAGES2050 is a novel Python 3.6+ programming language framework to boost bacteriophage research & therapy
Home-page: https://github.com/ptynecki/PHAGES2050
Author: Piotr Tynecki
Author-email: p.tynecki@doktoranci.pb.edu.pl
License: MIT
Download-URL: https://github.com/ptynecki/PHAGES2050/archive/v0.0.7.tar.gz
Keywords: bacteriophages,phages,phage therapy,phage research,amr,genome embedding,protein embedding
Platform: UNKNOWN
Classifier: Development Status :: 3 - Alpha
Classifier: License :: OSI Approved :: MIT License
Classifier: Programming Language :: Python :: 3.6
Requires-Python: >=3.6
